{
  "timestamp": "2025-04-11T14:45:49.745439",
  "bottlenecks_identified": 2,
  "optimizations_implemented": [
    {
      "type": "precomputed_collection",
      "description": "Created precomputed_timeseries collection",
      "details": "Generated time series data for 1000 products"
    },
    {
      "type": "precomputed_collection",
      "description": "Created precomputed_platform_stats collection",
      "details": "Generated statistics for 2 platforms"
    },
    {
      "type": "caching",
      "description": "Implemented scheduled refresh of precomputed collections",
      "details": "Set up refresh_precomputed_collections.py script to run every 6 hours"
    }
  ],
  "performance_metrics": []
}